[ 
   {
        "id": 1,
        "event": "seret",
        "name": "TAKEN1",
        "desc": "new with nisan willam  ",
        "img": "https://upload.wikimedia.org/wikipedia/he/thumb/f/f0/Taken_2_Poster.jpg/200px-Taken_2_Poster.jpg",
        },
    { 
        "id": 2,
        "status": 1,
        "name": "lecture",
        "desc": "Tomato and olives and cheese",
        "date" : "22/10/2019",
        "userId" : [1,2,3],
        "img": "https://food.fnr.sndimg.com/content/dam/images/food/fullset/2010/4/23/0/BX0204_greek-salad_s4x3.jpg.rend.hgtvcom.616.462.suffix/1529943050536.jpeg",
         },
         {
        "id": 3,
        "status": 1,
        "event": "seret",
        "name": "TAKEN1",
        "desc": "new with nisan willam  ",
        "date" : "22/10/2019",
        "userId" : [1,2,3],
        "img": "https://upload.wikimedia.org/wikipedia/he/thumb/f/f0/Taken_2_Poster.jpg/200px-Taken_2_Poster.jpg",
        },
        {
        "id": 4,
        "status": 1,
        "event": "seret",
        "name": "TAKEN1",
        "desc": "new with nisan willam  ",
        "date" : "22/10/2019",
        "userId" : [1,2,3],
        "img": "https://upload.wikimedia.org/wikipedia/he/thumb/f/f0/Taken_2_Poster.jpg/200px-Taken_2_Poster.jpg",
        }
]